securerun-0.1.0.dist-info/licenses/LICENSE
sr/__init__.py
sr/sr.py
securerun-0.1.0.dist-info/METADATA
securerun-0.1.0.dist-info/WHEEL
securerun-0.1.0.dist-info/entry_points.txt
securerun-0.1.0.dist-info/top_level.txt
securerun-0.1.0.dist-info/RECORD
