Metadata-Version: 2.4
Name: securerun
Version: 0.1.0
Summary: Secure-run utility for encrypted Python execution
Author: Viren
License: License & Disclaimer
Requires-Python: >=3.9
License-File: LICENSE
Requires-Dist: cryptography
Requires-Dist: colorama
Dynamic: license-file
